usb_can_analyzer/__init__.py
usb_can_analyzer/core.py
usb_can_analyzer/useful.py
usb_can_analyzer-2.0.0.dist-info/METADATA
usb_can_analyzer-2.0.0.dist-info/WHEEL
usb_can_analyzer-2.0.0.dist-info/top_level.txt
usb_can_analyzer-2.0.0.dist-info/RECORD
