Metadata-Version: 2.1
Name: usb-can-analyzer
Version: 2.0.0
Summary: Python library for the usb can analyzer.
Home-page: https://github.com/yncreahdf-robotics/usb_can_analyzer_py/tree/master/usb_can_analyzer
Author: UNKNOWN
Author-email: UNKNOWN
License: UNKNOWN
Platform: UNKNOWN
Classifier: Programming Language :: Python
Classifier: Natural Language :: English
Classifier: Operating System :: OS Independent
Classifier: Programming Language :: Python :: 3.5
Requires-Dist: pyserial
